aioec/__init__.py
aioec/client.py
aioec/emote.py
aioec/errors.py
aioec/http.py
aioec/utils.py
aioec-0.6.1.dist-info/COPYING
aioec-0.6.1.dist-info/METADATA
aioec-0.6.1.dist-info/WHEEL
aioec-0.6.1.dist-info/top_level.txt
aioec-0.6.1.dist-info/RECORD
