Metadata-Version: 2.1
Name: aioec
Version: 0.6.1
Summary: async client library for the Emote Collector API
Home-page: https://github.com/EmoteCollector/aioec
Author: io mintz
Author-email: io@mintz.cc
License: MIT
Platform: UNKNOWN
Classifier: Development Status :: 2 - Pre-Alpha
Classifier: Intended Audience :: Developers
Classifier: Topic :: Internet
Classifier: Topic :: Software Development :: Libraries
Classifier: Topic :: Software Development :: Libraries :: Python Modules
Classifier: Programming Language :: Python :: 3.5
Classifier: Programming Language :: Python :: 3.6
Classifier: Programming Language :: Python :: 3.7
Classifier: Operating System :: OS Independent
Classifier: License :: OSI Approved :: MIT License
Requires-Python: >=3.5.3
Requires-Dist: aiohttp (<3.7.0,>=3.6.0)
